django_file_inbox-0.1.0.dist-info/METADATA
django_file_inbox-0.1.0.dist-info/WHEEL
django_file_inbox-0.1.0.dist-info/licenses/LICENSE
django_file_inbox/__init__.py
django_file_inbox/apps.py
django_file_inbox/templates/django_file_inbox/_pagination.html
django_file_inbox/templates/django_file_inbox/inbox_email_template.html
django_file_inbox/templates/django_file_inbox/inbox_template.html
django_file_inbox/templates/django_file_inbox/processed/.gitkeep
django_file_inbox/templates/django_file_inbox/processed/inbox.html
django_file_inbox/templates/django_file_inbox/processed/inbox_email.html
django_file_inbox/templatetags/__init__.py
django_file_inbox/templatetags/custom_block.py
django_file_inbox/urls.py
django_file_inbox/views.py
django_file_inbox-0.1.0.dist-info/RECORD
