Metadata-Version: 2.1
Name: django-file-inbox
Version: 0.1.0
Summary: Simple inbox for Django file-based EmailBackend
Author-Email: Michael J. Nicholson <michjnich@outlook.com>
License: MIT
Classifier: Programming Language :: Python :: 3
Classifier: License :: OSI Approved :: MIT License
Classifier: Operating System :: OS Independent
Classifier: Framework :: Django
Project-URL: Homepage, https://github.com/michjnich/django-file-inbox
Project-URL: Issue tracker, https://github.com/michjnich/django-file-inbox/issues
Requires-Python: <4.0,>=3.10
Requires-Dist: django~=4.0
